YoungLion/Colors.py
YoungLion/DataModel.py
YoungLion/__init__.py
YoungLion/function.py
YoungLion/search.py
YoungLion/static/tex-mml-chtml.js
younglion-0.0.9.9.dist-info/licenses/AUTHORS.md
younglion-0.0.9.9.dist-info/licenses/LICENSE
younglion-0.0.9.9.dist-info/METADATA
younglion-0.0.9.9.dist-info/WHEEL
younglion-0.0.9.9.dist-info/top_level.txt
younglion-0.0.9.9.dist-info/RECORD
