Metadata-Version: 2.4
Name: YoungLion
Version: 0.0.9.9
Summary: Professional Python library with hierarchical data models (DDM), utilities, games, file operations, search, terminal styling, and rich debugging tools for developers.
Home-page: https://github.com/cavanshirpro/YoungLion
Author: Cavanşir Qurbanzadə
Author-email: Cavanşir Qurbanzadə <cavanshirpro@gmail.com>
Maintainer: Cavanşir Qurbanzadə
Maintainer-email: Cavanşir Qurbanzadə <cavanshirpro@gmail.com>
License: MIT
Project-URL: Homepage, https://github.com/Cavanshirpro/YoungLionPythonLibrary
Project-URL: Repository, https://github.com/Cavanshirpro/YoungLionPythonLibrary.git
Project-URL: Documentation, https://github.com/Cavanshirpro/YoungLionPythonLibrary#readme
Project-URL: Bug Tracker, https://github.com/Cavanshirpro/YoungLionPythonLibrary/issues
Project-URL: Source Code, https://github.com/Cavanshirpro/YoungLionPythonLibrary
Keywords: YoungLion,Young Lion,DDM,DataModel,utilities,games,file-operations,terminal-styling,debugging,search
Classifier: Development Status :: 4 - Beta
Classifier: Environment :: Console
Classifier: Intended Audience :: Developers
Classifier: License :: OSI Approved :: MIT License
Classifier: Natural Language :: English
Classifier: Natural Language :: Turkish
Classifier: Operating System :: OS Independent
Classifier: Operating System :: Microsoft :: Windows
Classifier: Operating System :: POSIX
Classifier: Operating System :: POSIX :: Linux
Classifier: Operating System :: MacOS
Classifier: Programming Language :: Python
Classifier: Programming Language :: Python :: 3
Classifier: Programming Language :: Python :: 3 :: Only
Classifier: Programming Language :: Python :: 3.7
Classifier: Programming Language :: Python :: 3.8
Classifier: Programming Language :: Python :: 3.9
Classifier: Programming Language :: Python :: 3.10
Classifier: Programming Language :: Python :: 3.11
Classifier: Programming Language :: Python :: 3.12
Classifier: Programming Language :: Python :: Implementation :: CPython
Classifier: Topic :: Software Development :: Libraries :: Python Modules
Classifier: Topic :: Utilities
Classifier: Topic :: Games/Entertainment
Classifier: Topic :: Office/Business
Classifier: Topic :: System :: Monitoring
Classifier: Typing :: Typed
Requires-Python: >=3.7
License-File: LICENSE
License-File: AUTHORS.md
Requires-Dist: PyYAML>=5.4
Requires-Dist: PyPDF2>=2.0.0
Requires-Dist: reportlab>=3.6.0
Requires-Dist: Pillow>=8.0.0
Requires-Dist: matplotlib>=3.3.0
Requires-Dist: tqdm>=4.50.0
Requires-Dist: paramiko>=2.7.0
Requires-Dist: pylatexenc>=2.0
Requires-Dist: markdown2>=2.3.0
Provides-Extra: dev
Requires-Dist: pytest>=6.0; extra == "dev"
Requires-Dist: pytest-cov>=2.10.0; extra == "dev"
Requires-Dist: black>=21.0; extra == "dev"
Requires-Dist: pylint>=2.8.0; extra == "dev"
Requires-Dist: mypy>=0.9; extra == "dev"
Requires-Dist: build>=0.10.0; extra == "dev"
Requires-Dist: twine>=4.0.0; extra == "dev"
Dynamic: author
Dynamic: home-page
Dynamic: license-file
Dynamic: maintainer
Dynamic: requires-python
